zoterosync/__init__.py
zoterosync/zoterosync.py
zoterosync/zoterosync_cli.py
zoterosync-0.1.3.dist-info/entry_points.txt
zoterosync-0.1.3.dist-info/LICENSE
zoterosync-0.1.3.dist-info/WHEEL
zoterosync-0.1.3.dist-info/METADATA
zoterosync-0.1.3.dist-info/RECORD
