Metadata-Version: 2.1
Name: zoterosync
Version: 0.1.3
Summary: it syncs zotero storage with a rclone remote
Home-page: https://gitlab.com/marceloakira/zoterosync
Author: Marcelo Akira Inuzuka
Author-email: marceloakira@ufg.br
Requires-Python: >=3
Classifier: License :: OSI Approved :: GNU General Public License v3 or later (GPLv3+)
Requires-Dist: click
Requires-Dist: pybtex>=0.24.0
Requires-Dist: python-dotenv>=0.15.0
Requires-Dist: python-rclone>=0.0.2
